patcheck.py
patcheck-1.12.0.dist-info/entry_points.txt
patcheck-1.12.0.dist-info/WHEEL
patcheck-1.12.0.dist-info/METADATA
patcheck-1.12.0.dist-info/RECORD
