Metadata-Version: 2.1
Name: patcheck
Version: 1.12.0
Summary: A CLI tool to validate user permission on the given BigQuery datasets, and return validation result as a csv file `check_result.csv`
Author: Worasit Daimongkol
Author-email: worasit.daimongkol@refinitiv.com
Requires-Python: >=3.6,<4.0
Classifier: Programming Language :: Python :: 3
Classifier: Programming Language :: Python :: 3.6
Classifier: Programming Language :: Python :: 3.7
Classifier: Programming Language :: Python :: 3.8
Classifier: Programming Language :: Python :: 3.9
